async_captcha_solver/__init__.py
async_captcha_solver/abc.py
async_captcha_solver/captcha_methods_mixin.py
async_captcha_solver/captcha_services.py
async_captcha_solver/http_client/abc.py
async_captcha_solver/http_client/aiohttp_client.py
async_captcha_solver-0.1.1.dist-info/METADATA
async_captcha_solver-0.1.1.dist-info/WHEEL
async_captcha_solver-0.1.1.dist-info/top_level.txt
async_captcha_solver-0.1.1.dist-info/RECORD
