Metadata-Version: 2.2
Name: async-captcha-solver
Version: 0.1.1
Summary: A versatile captcha solver module integrating popular captcha-solving services like 2Captcha, AntiCaptcha, and more.
Requires-Python: >=3.12
Requires-Dist: aiohttp>=3.11.11
